compas_gmsh/__init__.py
compas_gmsh/options.py
compas_gmsh/conversions/__init__.py
compas_gmsh/models/__init__.py
compas_gmsh/models/csg.py
compas_gmsh/models/mesh.py
compas_gmsh/models/model.py
compas_gmsh/models/shape.py
compas_gmsh/triangulation/__init__.py
compas_gmsh-0.4.4.dist-info/licenses/LICENSE.GPL
compas_gmsh-0.4.4.dist-info/licenses/LICENSE.MIT
compas_gmsh-0.4.4.dist-info/METADATA
compas_gmsh-0.4.4.dist-info/WHEEL
compas_gmsh-0.4.4.dist-info/top_level.txt
compas_gmsh-0.4.4.dist-info/RECORD
