Metadata-Version: 2.4
Name: compas_gmsh
Version: 0.4.4
Summary: COMPAS wrapper for the PYthon bindings of GMSH
Author-email: tom van mele <tom.v.mele@gmail.com>
Project-URL: Homepage, https://compas-dev.github.io/compas_gmsh
Project-URL: Repository, https://github.com/compas-dev/compas_gmsh
Keywords: compas,fea,meshing,gmsh
Classifier: Development Status :: 4 - Beta
Classifier: Topic :: Scientific/Engineering
Classifier: Programming Language :: Python
Classifier: Programming Language :: Python :: 3
Classifier: Programming Language :: Python :: 3.9
Classifier: Programming Language :: Python :: 3.10
Classifier: Programming Language :: Python :: 3.11
Requires-Python: >=3.9
License-File: LICENSE.GPL
License-File: LICENSE.MIT
Requires-Dist: compas>=2.1
Requires-Dist: gmsh
Provides-Extra: dev
Requires-Dist: attrs>=17.4; extra == "dev"
Requires-Dist: black>=22.12.0; extra == "dev"
Requires-Dist: bump-my-version; extra == "dev"
Requires-Dist: compas_invocations2; extra == "dev"
Requires-Dist: compas_viewer; extra == "dev"
Requires-Dist: invoke>=0.14; extra == "dev"
Requires-Dist: ruff; extra == "dev"
Requires-Dist: sphinx_compas2_theme; extra == "dev"
Requires-Dist: twine; extra == "dev"
Requires-Dist: wheel; extra == "dev"
Dynamic: license-file
